{
  "name": "Glass River",
  "ticks_per_beat": 480,
  "sections": [
    {
      "key": "Ab",
      "mode": "major",
      "bars": 24,
      "tempo": 76,
      "meter": "4/4",
      "voices": [
        {
          "name": "piano_melody",
          "behavior": "random_walk",
          "channel": 0,
          "program": 0,
          "low": 65,
          "high": 88,
          "density": 0.25,
          "velocity_range": [55, 80],
          "note_lengths": [3, 4, 6, 8],
          "note_length_weights": [0.15, 0.35, 0.3, 0.2],
          "phrase_length": 4,
          "params": { "leap_probability": 0.1, "humanize": "expressive" }
        },
        {
          "name": "guitar_arp",
          "behavior": "arpeggio",
          "channel": 1,
          "program": 25,
          "low": 48,
          "high": 72,
          "density": 0.5,
          "velocity_range": [45, 65],
          "phrase_length": 4,
          "params": { "pattern": "up_down", "note_length": 2, "degree": 1, "humanize": "natural" }
        },
        {
          "name": "synth_pad",
          "behavior": "random_walk",
          "channel": 2,
          "program": 89,
          "low": 48,
          "high": 67,
          "density": 0.08,
          "velocity_range": [35, 55],
          "note_lengths": [8, 12, 16],
          "note_length_weights": [0.3, 0.4, 0.3],
          "phrase_length": 8,
          "params": { "leap_probability": 0.03, "humanize": "legato" }
        },
        {
          "name": "bass",
          "behavior": "random_walk",
          "channel": 3,
          "program": 33,
          "low": 36,
          "high": 53,
          "density": 0.12,
          "velocity_range": [50, 70],
          "note_lengths": [6, 8, 12],
          "note_length_weights": [0.25, 0.4, 0.35],
          "phrase_length": 4,
          "params": { "leap_probability": 0.04 }
        }
      ]
    },
    {
      "key": "Db",
      "mode": "major",
      "bars": 24,
      "tempo": 76,
      "meter": "4/4",
      "voices": [
        {
          "name": "piano_melody",
          "behavior": "random_walk",
          "channel": 0,
          "program": 0,
          "low": 65,
          "high": 88,
          "density": 0.28,
          "velocity_range": [55, 82],
          "note_lengths": [3, 4, 6, 8],
          "note_length_weights": [0.2, 0.35, 0.3, 0.15],
          "phrase_length": 4,
          "params": { "leap_probability": 0.1 }
        },
        {
          "name": "guitar_arp",
          "behavior": "arpeggio",
          "channel": 1,
          "program": 25,
          "low": 48,
          "high": 72,
          "density": 0.5,
          "velocity_range": [45, 65],
          "phrase_length": 4,
          "params": { "pattern": "up", "note_length": 2, "degree": 1 }
        },
        {
          "name": "synth_pad",
          "behavior": "random_walk",
          "channel": 2,
          "program": 89,
          "low": 48,
          "high": 67,
          "density": 0.08,
          "velocity_range": [35, 55],
          "note_lengths": [8, 12, 16],
          "note_length_weights": [0.3, 0.4, 0.3],
          "phrase_length": 8,
          "params": { "leap_probability": 0.03 }
        },
        {
          "name": "bass",
          "behavior": "random_walk",
          "channel": 3,
          "program": 33,
          "low": 36,
          "high": 53,
          "density": 0.12,
          "velocity_range": [50, 70],
          "note_lengths": [6, 8, 12],
          "note_length_weights": [0.25, 0.4, 0.35],
          "phrase_length": 4,
          "params": { "leap_probability": 0.04 }
        }
      ]
    },
    {
      "key": "F",
      "mode": "minor",
      "bars": 24,
      "tempo": 76,
      "meter": "4/4",
      "voices": [
        {
          "name": "piano_melody",
          "behavior": "random_walk",
          "channel": 0,
          "program": 0,
          "low": 65,
          "high": 88,
          "density": 0.22,
          "velocity_range": [50, 78],
          "note_lengths": [4, 6, 8, 12],
          "note_length_weights": [0.15, 0.3, 0.35, 0.2],
          "phrase_length": 4,
          "params": { "leap_probability": 0.08 }
        },
        {
          "name": "guitar_arp",
          "behavior": "arpeggio",
          "channel": 1,
          "program": 25,
          "low": 48,
          "high": 72,
          "density": 0.45,
          "velocity_range": [40, 60],
          "phrase_length": 4,
          "params": { "pattern": "up_down", "note_length": 2, "degree": 1 }
        },
        {
          "name": "flute",
          "behavior": "random_walk",
          "channel": 4,
          "program": 73,
          "low": 72,
          "high": 91,
          "density": 0.1,
          "velocity_range": [40, 60],
          "note_lengths": [6, 8, 12, 16],
          "note_length_weights": [0.15, 0.3, 0.35, 0.2],
          "phrase_length": 8,
          "params": { "leap_probability": 0.05, "humanize": "legato" }
        },
        {
          "name": "synth_pad",
          "behavior": "random_walk",
          "channel": 2,
          "program": 89,
          "low": 48,
          "high": 67,
          "density": 0.08,
          "velocity_range": [35, 55],
          "note_lengths": [8, 12, 16],
          "note_length_weights": [0.3, 0.4, 0.3],
          "phrase_length": 8,
          "params": { "leap_probability": 0.03 }
        },
        {
          "name": "bass",
          "behavior": "random_walk",
          "channel": 3,
          "program": 33,
          "low": 36,
          "high": 53,
          "density": 0.12,
          "velocity_range": [50, 70],
          "note_lengths": [6, 8, 12],
          "note_length_weights": [0.25, 0.4, 0.35],
          "phrase_length": 4,
          "params": { "leap_probability": 0.04 }
        }
      ]
    },
    {
      "key": "Eb",
      "mode": "major",
      "bars": 24,
      "tempo": 76,
      "meter": "4/4",
      "voices": [
        {
          "name": "piano_melody",
          "behavior": "random_walk",
          "channel": 0,
          "program": 0,
          "low": 65,
          "high": 88,
          "density": 0.3,
          "velocity_range": [58, 85],
          "note_lengths": [2, 3, 4, 6],
          "note_length_weights": [0.15, 0.3, 0.35, 0.2],
          "phrase_length": 4,
          "params": { "leap_probability": 0.12 }
        },
        {
          "name": "guitar_arp",
          "behavior": "arpeggio",
          "channel": 1,
          "program": 25,
          "low": 48,
          "high": 72,
          "density": 0.55,
          "velocity_range": [48, 68],
          "phrase_length": 4,
          "params": { "pattern": "up_down", "note_length": 2, "degree": 1 }
        },
        {
          "name": "flute",
          "behavior": "random_walk",
          "channel": 4,
          "program": 73,
          "low": 72,
          "high": 91,
          "density": 0.12,
          "velocity_range": [42, 62],
          "note_lengths": [4, 6, 8, 12],
          "note_length_weights": [0.15, 0.3, 0.35, 0.2],
          "phrase_length": 8,
          "params": { "leap_probability": 0.06 }
        },
        {
          "name": "synth_pad",
          "behavior": "random_walk",
          "channel": 2,
          "program": 89,
          "low": 48,
          "high": 67,
          "density": 0.1,
          "velocity_range": [38, 58],
          "note_lengths": [8, 12, 16],
          "note_length_weights": [0.3, 0.4, 0.3],
          "phrase_length": 8,
          "params": { "leap_probability": 0.03 }
        },
        {
          "name": "bass",
          "behavior": "random_walk",
          "channel": 3,
          "program": 33,
          "low": 36,
          "high": 53,
          "density": 0.14,
          "velocity_range": [52, 72],
          "note_lengths": [4, 6, 8],
          "note_length_weights": [0.25, 0.4, 0.35],
          "phrase_length": 4,
          "params": { "leap_probability": 0.04 }
        }
      ]
    },
    {
      "key": "F",
      "mode": "minor",
      "bars": 16,
      "tempo": 74,
      "meter": "4/4",
      "voices": [
        {
          "name": "piano_melody",
          "behavior": "random_walk",
          "channel": 0,
          "program": 0,
          "low": 65,
          "high": 88,
          "density": 0.2,
          "velocity_range": [50, 75],
          "note_lengths": [4, 6, 8, 12],
          "note_length_weights": [0.1, 0.3, 0.35, 0.25],
          "phrase_length": 4,
          "params": { "leap_probability": 0.06 }
        },
        {
          "name": "guitar_arp",
          "behavior": "arpeggio",
          "channel": 1,
          "program": 25,
          "low": 48,
          "high": 72,
          "density": 0.4,
          "velocity_range": [40, 58],
          "phrase_length": 4,
          "params": { "pattern": "up", "note_length": 3, "degree": 1 }
        },
        {
          "name": "synth_pad",
          "behavior": "random_walk",
          "channel": 2,
          "program": 89,
          "low": 48,
          "high": 67,
          "density": 0.06,
          "velocity_range": [30, 50],
          "note_lengths": [12, 16],
          "note_length_weights": [0.4, 0.6],
          "phrase_length": 8,
          "params": { "leap_probability": 0.02 }
        },
        {
          "name": "bass",
          "behavior": "random_walk",
          "channel": 3,
          "program": 33,
          "low": 36,
          "high": 53,
          "density": 0.1,
          "velocity_range": [48, 65],
          "note_lengths": [8, 12, 16],
          "note_length_weights": [0.3, 0.4, 0.3],
          "phrase_length": 4,
          "params": { "leap_probability": 0.03 }
        }
      ]
    },
    {
      "key": "Ab",
      "mode": "major",
      "bars": 32,
      "tempo": 76,
      "meter": "4/4",
      "voices": [
        {
          "name": "piano_melody",
          "behavior": "random_walk",
          "channel": 0,
          "program": 0,
          "low": 65,
          "high": 88,
          "density": 0.28,
          "velocity_range": [55, 82],
          "note_lengths": [3, 4, 6, 8],
          "note_length_weights": [0.15, 0.35, 0.3, 0.2],
          "phrase_length": 4,
          "params": { "leap_probability": 0.1 }
        },
        {
          "name": "guitar_arp",
          "behavior": "arpeggio",
          "channel": 1,
          "program": 25,
          "low": 48,
          "high": 72,
          "density": 0.5,
          "velocity_range": [45, 65],
          "phrase_length": 4,
          "params": { "pattern": "up_down", "note_length": 2, "degree": 1 }
        },
        {
          "name": "flute",
          "behavior": "random_walk",
          "channel": 4,
          "program": 73,
          "low": 72,
          "high": 91,
          "density": 0.08,
          "velocity_range": [38, 55],
          "note_lengths": [8, 12, 16],
          "note_length_weights": [0.3, 0.4, 0.3],
          "phrase_length": 8,
          "params": { "leap_probability": 0.04 }
        },
        {
          "name": "synth_pad",
          "behavior": "random_walk",
          "channel": 2,
          "program": 89,
          "low": 48,
          "high": 67,
          "density": 0.08,
          "velocity_range": [35, 55],
          "note_lengths": [8, 12, 16],
          "note_length_weights": [0.3, 0.4, 0.3],
          "phrase_length": 8,
          "params": { "leap_probability": 0.03 }
        },
        {
          "name": "bass",
          "behavior": "random_walk",
          "channel": 3,
          "program": 33,
          "low": 36,
          "high": 53,
          "density": 0.12,
          "velocity_range": [50, 70],
          "note_lengths": [6, 8, 12],
          "note_length_weights": [0.25, 0.4, 0.35],
          "phrase_length": 4,
          "params": { "leap_probability": 0.04 }
        }
      ]
    },
    {
      "key": "Db",
      "mode": "lydian",
      "bars": 24,
      "tempo": 74,
      "meter": "4/4",
      "voices": [
        {
          "name": "piano_melody",
          "behavior": "random_walk",
          "channel": 0,
          "program": 0,
          "low": 65,
          "high": 88,
          "density": 0.2,
          "velocity_range": [48, 72],
          "note_lengths": [4, 6, 8, 12],
          "note_length_weights": [0.1, 0.25, 0.35, 0.3],
          "phrase_length": 4,
          "params": { "leap_probability": 0.06 }
        },
        {
          "name": "guitar_arp",
          "behavior": "arpeggio",
          "channel": 1,
          "program": 25,
          "low": 48,
          "high": 72,
          "density": 0.4,
          "velocity_range": [40, 58],
          "phrase_length": 4,
          "params": { "pattern": "up", "note_length": 3, "degree": 1 }
        },
        {
          "name": "synth_pad",
          "behavior": "random_walk",
          "channel": 2,
          "program": 89,
          "low": 48,
          "high": 67,
          "density": 0.06,
          "velocity_range": [30, 48],
          "note_lengths": [12, 16],
          "note_length_weights": [0.4, 0.6],
          "phrase_length": 8,
          "params": { "leap_probability": 0.02 }
        },
        {
          "name": "bass",
          "behavior": "random_walk",
          "channel": 3,
          "program": 33,
          "low": 36,
          "high": 53,
          "density": 0.1,
          "velocity_range": [45, 62],
          "note_lengths": [8, 12, 16],
          "note_length_weights": [0.3, 0.4, 0.3],
          "phrase_length": 4,
          "params": { "leap_probability": 0.03 }
        }
      ]
    },
    {
      "key": "Ab",
      "mode": "major",
      "bars": 16,
      "tempo": 72,
      "meter": "4/4",
      "voices": [
        {
          "name": "piano_melody",
          "behavior": "random_walk",
          "channel": 0,
          "program": 0,
          "low": 65,
          "high": 88,
          "density": 0.15,
          "velocity_range": [42, 65],
          "note_lengths": [6, 8, 12, 16],
          "note_length_weights": [0.15, 0.3, 0.35, 0.2],
          "phrase_length": 4,
          "params": { "leap_probability": 0.04 }
        },
        {
          "name": "guitar_arp",
          "behavior": "arpeggio",
          "channel": 1,
          "program": 25,
          "low": 48,
          "high": 72,
          "density": 0.35,
          "velocity_range": [35, 52],
          "phrase_length": 4,
          "params": { "pattern": "up", "note_length": 3, "degree": 1 }
        },
        {
          "name": "synth_pad",
          "behavior": "random_walk",
          "channel": 2,
          "program": 89,
          "low": 48,
          "high": 67,
          "density": 0.05,
          "velocity_range": [28, 45],
          "note_lengths": [12, 16],
          "note_length_weights": [0.4, 0.6],
          "phrase_length": 8,
          "params": { "leap_probability": 0.02 }
        },
        {
          "name": "bass",
          "behavior": "random_walk",
          "channel": 3,
          "program": 33,
          "low": 36,
          "high": 53,
          "density": 0.08,
          "velocity_range": [40, 58],
          "note_lengths": [8, 12, 16],
          "note_length_weights": [0.25, 0.4, 0.35],
          "phrase_length": 4,
          "params": { "leap_probability": 0.03 }
        }
      ]
    }
  ]
}
